LICENSE
LICENSES.md
MANIFEST.in
README.md
setup.cfg
setup.py
mmcv/__init__.py
mmcv/version.py
mmcv/arraymisc/__init__.py
mmcv/arraymisc/quantization.py
mmcv/cnn/__init__.py
mmcv/cnn/alexnet.py
mmcv/cnn/builder.py
mmcv/cnn/resnet.py
mmcv/cnn/vgg.py
mmcv/cnn/bricks/__init__.py
mmcv/cnn/bricks/activation.py
mmcv/cnn/bricks/context_block.py
mmcv/cnn/bricks/conv.py
mmcv/cnn/bricks/conv2d_adaptive_padding.py
mmcv/cnn/bricks/conv_module.py
mmcv/cnn/bricks/conv_ws.py
mmcv/cnn/bricks/depthwise_separable_conv_module.py
mmcv/cnn/bricks/drop.py
mmcv/cnn/bricks/generalized_attention.py
mmcv/cnn/bricks/hsigmoid.py
mmcv/cnn/bricks/hswish.py
mmcv/cnn/bricks/non_local.py
mmcv/cnn/bricks/norm.py
mmcv/cnn/bricks/padding.py
mmcv/cnn/bricks/plugin.py
mmcv/cnn/bricks/registry.py
mmcv/cnn/bricks/scale.py
mmcv/cnn/bricks/swish.py
mmcv/cnn/bricks/transformer.py
mmcv/cnn/bricks/upsample.py
mmcv/cnn/bricks/wrappers.py
mmcv/cnn/rfsearch/__init__.py
mmcv/cnn/rfsearch/operator.py
mmcv/cnn/rfsearch/search.py
mmcv/cnn/rfsearch/utils.py
mmcv/cnn/utils/__init__.py
mmcv/cnn/utils/flops_counter.py
mmcv/cnn/utils/fuse_conv_bn.py
mmcv/cnn/utils/sync_bn.py
mmcv/cnn/utils/weight_init.py
mmcv/device/__init__.py
mmcv/device/_functions.py
mmcv/device/scatter_gather.py
mmcv/device/utils.py
mmcv/device/ipu/__init__.py
mmcv/device/ipu/dataloader.py
mmcv/device/ipu/hierarchical_data_manager.py
mmcv/device/ipu/hook_wrapper.py
mmcv/device/ipu/model_wrapper.py
mmcv/device/ipu/runner.py
mmcv/device/ipu/utils.py
mmcv/device/mlu/__init__.py
mmcv/device/mlu/_functions.py
mmcv/device/mlu/data_parallel.py
mmcv/device/mlu/distributed.py
mmcv/device/mlu/scatter_gather.py
mmcv/device/mps/__init__.py
mmcv/device/mps/data_parallel.py
mmcv/device/npu/__init__.py
mmcv/device/npu/data_parallel.py
mmcv/device/npu/distributed.py
mmcv/engine/__init__.py
mmcv/engine/test.py
mmcv/fileio/__init__.py
mmcv/fileio/file_client.py
mmcv/fileio/io.py
mmcv/fileio/parse.py
mmcv/fileio/handlers/__init__.py
mmcv/fileio/handlers/base.py
mmcv_full.egg-info/PKG-INFO
mmcv_full.egg-info/SOURCES.txt
mmcv_full.egg-info/dependency_links.txt
mmcv_full.egg-info/not-zip-safe
mmcv_full.egg-info/requires.txt
mmcv_full.egg-info/top_level.txt
